<?xml version="1.0" encoding="utf-8"?>
<Deployment xmlns="http://schemas.microsoft.com/windowsphone/2009/deployment" AppPlatformVersion="7.0">
  <App xmlns="" ProductID="{7ea3b22b-9be9-4b2b-9bf3-2b68f26d4418}" Title="Hanoi" RuntimeType="Silverlight" Version="1.0.0.0" Genre="apps.games" Author="Elucidsoft" Description="" Publisher="Elucidsoft">
    <IconPath IsRelative="true" IsResource="false">ApplicationIcon.png</IconPath>
    <Capabilities>
      <Capability Name="ID_CAP_NETWORKING" />
    </Capabilities>
    <Tasks>
      <DefaultTask Name="_default" NavigationPage="MainPage.xaml" />
    </Tasks>
    <Tokens>
      <PrimaryToken TokenID="HanoiToken" TaskName="_default">
        <TemplateType5>
          <BackgroundImageURI IsRelative="true" IsResource="false">Background.png</BackgroundImageURI>
          <Count>0</Count>
          <Title>Hanoi</Title>
        </TemplateType5>
      </PrimaryToken>
    </Tokens>
  </App>
</Deployment>